src/Basic_controller.v
module basic_controller (
    input wire Clock,
    input wire Reset,
    output reg Red,
    output reg Yellow,
    output reg Green
);
    parameter RED = 2'b00;
    parameter YELLOW = 2'b01;
    parameter GREEN = 2'b10;
    parameter All_RED = 2'b11;
    reg [1:0] Current_state;
    reg [1:0] Next_state;
    reg [3:0] timer;
    reg [3:0] state_duration;

    always @(*) begin
    case (Current_state)
        RED:       state_duration = 4'd5;
        YELLOW:    state_duration = 4'd3;
        GREEN:     state_duration = 4'd10;
        All_RED:   state_duration = 4'd2;
        default:   state_duration = 4'd5;
    endcase
end
always @(posedge Clock or posedge Reset) begin

    if (Reset) begin
        Current_state  <= RED;
        timer <= 4'd0;
    end

    else if (timer == state_duration - 1) begin
        Current_state <= Next_state;
        timer <= 4'd0;
    end

    else begin
        timer <= timer + 4'd1;
    end
end
always @(*) begin
    Next_state=Current_state;
    case (Current_state)
        RED:begin
            Next_state=YELLOW;
        end 
        YELLOW:begin
            Next_state=GREEN;
        end
        GREEN:begin
            Next_state=All_RED;
        end
        All_RED:begin
            Next_state=RED;
        end
        default:Next_state=RED;
    endcase
end
always @(*) begin
    Red=1'b0;
    Yellow=1'b0;
    Green=1'b0;
    case (Current_state)
        RED:begin 
            Red=1'b1;
        end
        YELLOW:begin 
            Yellow=1'b1;
        end
        GREEN:begin 
            Green=1'b1;
        end
        All_RED:begin Red=1'b1;
        Yellow=1'b1;
        Green=1'b1;
        end
        default:begin Red=1'b0;
        Yellow=1'b0;
        Green=1'b0;
        end
    endcase
end

endmodule

testbenches/TB_Basic_controller.v
module tb_basic_controller;

reg Clock;
reg Reset;

wire Red;
wire Yellow;
wire Green;

basic_controller dut (
    .Clock(Clock),
    .Reset(Reset),
    .Red(Red),
    .Yellow(Yellow),
    .Green(Green)
);

always #5 Clock = ~Clock;

initial begin

    $dumpfile("basic_controller.vcd");
    $dumpvars(0, tb_basic_controller);

    $monitor("Time=%0t | Reset=%b | Red=%b Yellow=%b Green=%b",$time, Reset, Red, Yellow, Green);
    Clock = 0;Reset = 1;#10;
    Reset = 0;
    #220;

    $finish;
end

endmodule

basic_controller.vcd
$date
	Sun Sep 27 22:01:52 2026
$end
$version
	Icarus Verilog
$end
$timescale
	1s
$end
$scope module tb_basic_controller $end
$var wire 1 ! Yellow $end
$var wire 1 " Red $end
$var wire 1 # Green $end
$var reg 1 $ Clock $end
$var reg 1 % Reset $end
$scope module dut $end
$var wire 1 $ Clock $end
$var wire 1 % Reset $end
$var parameter 2 & All_RED $end
$var parameter 2 ' GREEN $end
$var parameter 2 ( RED $end
$var parameter 2 ) YELLOW $end
$var reg 2 * Current_state [1:0] $end
$var reg 1 # Green $end
$var reg 2 + Next_state [1:0] $end
$var reg 1 " Red $end
$var reg 1 ! Yellow $end
$var reg 4 , state_duration [3:0] $end
$var reg 4 - timer [3:0] $end
$upscope $end
$upscope $end
$enddefinitions $end
$comment Show the parameter values. $end
$dumpall
b1 )
b0 (
b10 '
b11 &
$end
#0
$dumpvars
b0 -
b101 ,
b1 +
b0 *
1%
0$
0#
1"
0!
$end
#5
1$
#10
0$
0%
#15
b1 -
1$
#20
0$
#25
b10 -
1$
#30
0$
#35
b11 -
1$
#40
0$
#45
b100 -
1$
#50
0$
#55
b11 ,
b10 +
1!
0"
b0 -
b1 *
1$
#60
0$
#65
b1 -
1$
#70
0$
#75
b10 -
1$
#80
0$
#85
1#
0!
b11 +
b1010 ,
b0 -
b10 *
1$
#90
0$
#95
b1 -
1$
#100
0$
#105
b10 -
1$
#110
0$
#115
b11 -
1$
#120
0$
#125
b100 -
1$
#130
0$
#135
b101 -
1$
#140
0$
#145
b110 -
1$
#150
0$
#155
b111 -
1$
#160
0$
#165
b1000 -
1$
#170
0$
#175
b1001 -
1$
#180
0$
#185
b10 ,
b0 +
1!
1"
1#
b0 -
b11 *
1$
#190
0$
#195
b1 -
1$
#200
0$
#205
0#
0!
1"
b1 +
b101 ,
b0 -
b0 *
1$
#210
0$
#215
b1 -
1$
#220
0$
#225
b10 -
1$
