src/Traffic_Controller.v
module Traffic_Controller (
    input wire Clock,
    input wire Reset,
    input wire Emergency,
    output reg Emergency_out,
    output reg Red,
    output reg Yellow,
    output reg Green 
);
    parameter RED = 3'b000;
    parameter YELLOW = 3'b001;
    parameter GREEN = 3'b010;
    parameter All_RED = 3'b011;
    parameter EMERGENCY = 3'b100;
    reg [2:0] Current_state;
    reg [2:0] Next_state;
    reg [2:0] Previous_state;
    reg [3:0] timer;
    reg [3:0] state_duration;
   always @(*) begin
    case (Current_state)
        RED:       state_duration = 4'd5;
        YELLOW:    state_duration = 4'd3;
        GREEN:     state_duration = 4'd10;
        All_RED:   state_duration = 4'd2;
        EMERGENCY: state_duration = 4'd0;
        default:   state_duration = 4'd5;
    endcase
end
always @(posedge Clock or posedge Reset) begin

    if (Reset) begin
        Current_state  <= RED;
        Previous_state <= RED;
        timer <= 4'd0;
    end

    else if (Emergency && Current_state != EMERGENCY) begin
        Previous_state <= Current_state;
        Current_state  <= EMERGENCY;
        timer <= 4'd0;
    end

    else if (Current_state == EMERGENCY && !Emergency) begin
        Current_state <= Previous_state;
        timer <= 4'd0;
    end

    else if (timer == state_duration - 1) begin
        Current_state <= Next_state;
        timer <= 4'd0;
    end

    else begin
        timer <= timer + 4'd1;
    end
end
always @(*) begin
    Next_state=Current_state;
    case (Current_state)
        RED:begin
            Next_state=YELLOW;
        end 
        YELLOW:begin
            Next_state=GREEN;
        end
        GREEN:begin
            Next_state=All_RED;
        end
        All_RED:begin
            Next_state=RED;
        end
        EMERGENCY: begin
            if (!Emergency) begin
                Next_state=Previous_state;
            end else begin
                Next_state=EMERGENCY;
            end
        end
        default:Next_state=RED;
    endcase
end
always @(*) begin
    Red=1'b0;
    Yellow=1'b0;
    Green=1'b0;
    Emergency_out=1'b0;
    case (Current_state)
        RED:begin 
            Red=1'b1;
        end
        YELLOW:begin 
            Yellow=1'b1;
        end
        GREEN:begin 
            Green=1'b1;
        end
        All_RED:begin Red=1'b1;
        Yellow=1'b1;
        Green=1'b1;
        end
        EMERGENCY:begin 
            Emergency_out=1'b1;
            Red=1'b1;
        end
        default:begin Red=1'b0;
        Yellow=1'b0;
        Green=1'b0;
        Emergency_out=1'b0;
        end
    endcase
end
endmodule

testbenches/PHASE_B_verification_tb.v
`timescale 1ns/1ps

module PHASE_B_verification_tb;

reg Clock;
reg Reset;
reg Emergency;

wire Red;
wire Yellow;
wire Green;
wire Emergency_out;

Traffic_Controller DUT (
    .Clock(Clock),
    .Reset(Reset),
    .Emergency(Emergency),
    .Red(Red),
    .Yellow(Yellow),
    .Green(Green),
    .Emergency_out(Emergency_out)
);

always #5 Clock = ~Clock;

initial begin

    $dumpfile("Verification.vcd");
    $dumpvars(0, PHASE_B_verification_tb);

    $monitor(
        "Time=%0t | Reset=%b | Emergency=%b | State=%b | Timer=%d | Red=%b | Yellow=%b | Green=%b | Emergency_out=%b",
        $time, Reset, Emergency,
        DUT.Current_state, DUT.timer,
        Red, Yellow, Green, Emergency_out
    );

    Clock = 1'b0;
    Reset = 1'b1;Emergency = 1'b0;#12;
    Reset = 1'b0;#10;Emergency = 1'b1;#10;
    Emergency = 1'b0;#10;
    wait (DUT.Current_state == 3'b001);#2;
    Emergency = 1'b1;#10;
    Emergency = 1'b0;#10;
    wait (DUT.Current_state == 3'b010);#2;
    Emergency = 1'b1;#10;
    Emergency = 1'b0;#10;
    wait (DUT.Current_state == 3'b011);#2;
    Emergency = 1'b1;#10;
    Emergency = 1'b0;#30;
    $finish;

end

endmodule

src/Verification.vcd
$date
	Sun Sep 20 14:05:45 2026
$end
$version
	Icarus Verilog
$end
$timescale
	1ps
$end
$scope module PHASE_B_verification_tb $end
$var wire 1 ! Yellow $end
$var wire 1 " Red $end
$var wire 1 # Green $end
$var wire 1 $ Emergency_out $end
$var reg 1 % Clock $end
$var reg 1 & Emergency $end
$var reg 1 ' Reset $end
$scope module DUT $end
$var wire 1 % Clock $end
$var wire 1 & Emergency $end
$var wire 1 ' Reset $end
$var parameter 3 ( All_RED $end
$var parameter 3 ) EMERGENCY $end
$var parameter 3 * GREEN $end
$var parameter 3 + RED $end
$var parameter 3 , YELLOW $end
$var reg 3 - Current_state [2:0] $end
$var reg 1 $ Emergency_out $end
$var reg 1 # Green $end
$var reg 3 . Next_state [2:0] $end
$var reg 3 / Previous_state [2:0] $end
$var reg 1 " Red $end
$var reg 1 ! Yellow $end
$var reg 4 0 state_duration [3:0] $end
$var reg 4 1 timer [3:0] $end
$upscope $end
$upscope $end
$enddefinitions $end
$comment Show the parameter values. $end
$dumpall
b1 ,
b0 +
b10 *
b100 )
b11 (
$end
#0
$dumpvars
b0 1
b101 0
b0 /
b1 .
b0 -
1'
0&
0%
0$
0#
1"
0!
$end
#5000
1%
#10000
0%
#12000
0'
#15000
b1 1
1%
#20000
0%
#22000
b1 .
1&
#25000
b0 0
1$
1"
b100 .
b0 1
b100 -
1%
#30000
0%
#32000
b0 .
0&
#35000
0$
1"
b101 0
b1 .
b0 -
1%
#40000
0%
#45000
b1 1
1%
#50000
0%
#55000
b10 1
1%
#60000
0%
#65000
b11 1
1%
#70000
0%
#75000
b100 1
1%
#80000
0%
#85000
b11 0
1!
0"
b10 .
b0 1
b1 -
1%
#87000
b10 .
1&
#90000
0%
#95000
1"
1$
0!
b0 0
b100 .
b100 -
b1 /
1%
#97000
b1 .
0&
#100000
0%
#105000
b11 0
1!
0$
0"
b10 .
b1 -
1%
#110000
0%
#115000
b1 1
1%
#120000
0%
#125000
b10 1
1%
#130000
0%
#135000
1#
0!
b1010 0
b11 .
b0 1
b10 -
1%
#137000
b11 .
1&
#140000
0%
#145000
b0 0
1"
1$
0#
b100 .
b100 -
b10 /
1%
#147000
b10 .
0&
#150000
0%
#155000
1#
0$
0"
b1010 0
b11 .
b10 -
1%
#160000
0%
#165000
b1 1
1%
#170000
0%
#175000
b10 1
1%
#180000
0%
#185000
b11 1
1%
#190000
0%
#195000
b100 1
1%
#200000
0%
#205000
b101 1
1%
#210000
0%
#215000
b110 1
1%
#220000
0%
#225000
b111 1
1%
#230000
0%
#235000
b1000 1
1%
#240000
0%
#245000
b1001 1
1%
#250000
0%
#255000
b10 0
1!
1"
1#
b0 .
b0 1
b11 -
1%
#257000
b0 .
1&
#260000
0%
#265000
1$
0#
0!
1"
b0 0
b100 .
b100 -
b11 /
1%
#267000
b11 .
0&
#270000
0%
#275000
b10 0
1#
1!
0$
1"
b0 .
b11 -
1%
#280000
0%
#285000
b1 1
1%
#290000
0%
#295000
0#
0!
1"
b101 0
b1 .
b0 1
b0 -
1%
